redisimp/VERSION
redisimp/__init__.py
redisimp/api.py
redisimp/cli.py
redisimp/crc64.py
redisimp/multi.py
redisimp/rdbparser.py
redisimp/version.py
redisimp-0.3.0.dist-info/LICENSE
redisimp-0.3.0.dist-info/METADATA
redisimp-0.3.0.dist-info/WHEEL
redisimp-0.3.0.dist-info/entry_points.txt
redisimp-0.3.0.dist-info/top_level.txt
redisimp-0.3.0.dist-info/RECORD
