Metadata-Version: 2.1
Name: redisimp
Version: 0.3.0
Summary: Redis Import tool, copy data from one redis instance into another or into a cluster.
Home-page: https://github.com/happybits/redisimp
Author: John Loehrer
Author-email: 72squared@gmail.com
License: MIT
Download-URL: https://github.com/72squared/redisimp/archive/0.3.0.tar.gz
Platform: UNKNOWN
Classifier: Development Status :: 4 - Beta
Classifier: Programming Language :: Python
Classifier: Programming Language :: Python
Classifier: Programming Language :: Python :: Implementation :: CPython
Classifier: Programming Language :: Python :: Implementation :: PyPy
Classifier: Programming Language :: Python :: 2
Classifier: Programming Language :: Python :: 2.7
Classifier: Programming Language :: Python :: 3
Classifier: Programming Language :: Python :: 3.3
Classifier: Programming Language :: Python :: 3.4
Classifier: Programming Language :: Python :: 3.5
Classifier: Environment :: Web Environment
Classifier: Operating System :: POSIX
Requires-Dist: redis (>=2.10.2)
Requires-Dist: redislite (>=3.0.0)
Requires-Dist: six
